playpen.py
playpen-0.0.1.dist-info/METADATA
playpen-0.0.1.dist-info/WHEEL
playpen-0.0.1.dist-info/licenses/LICENSE
playpen-0.0.1.dist-info/RECORD
