Metadata-Version: 2.1
Name: playpen
Version: 0.0.1
Summary: A little library for interactive fun and learning
Project-URL: Homepage, https://github.com/math4tots/playpen
Project-URL: Bug Tracker, https://github.com/math4tots/playpen/issues
Author: math4tots
License-File: LICENSE
Classifier: License :: OSI Approved :: MIT License
Classifier: Operating System :: OS Independent
Classifier: Programming Language :: Python :: 3
Requires-Python: >=3.7
